filesecure/__init__.py
filesecure/main.py
filesecure-0.7.0.dist-info/LICENSE
filesecure-0.7.0.dist-info/METADATA
filesecure-0.7.0.dist-info/WHEEL
filesecure-0.7.0.dist-info/entry_points.txt
filesecure-0.7.0.dist-info/top_level.txt
filesecure-0.7.0.dist-info/RECORD
