Metadata-Version: 2.1
Name: filesecure
Version: 0.7.0
Summary: A file encryption and decryption tool
Home-page: https://github.com/tbounsiar/filesecure
Author: Tahar BOUNSIAR
Author-email: tbounsiar@gmail.com
License-File: LICENSE
Requires-Dist: cryptography
